{"name":"therapist","intents":[{"intent":"General_Ending","examples":[{"text":"I'm leaving now"},{"text":"Bye now"},{"text":"Bye bye"},{"text":"That is all"},{"text":"Thanks very much, bye!"},{"text":"Thanks, bye!"},{"text":"Thank you for your time"},{"text":"Stop talking to me"},{"text":"Stop doing this"},{"text":"Shut up"},{"text":"See you"},{"text":"See you later"},{"text":"Ok goodbye"},{"text":"It was nice chatting with you"},{"text":"Catch you later"},{"text":"Im good thank you"},{"text":"Im done"},{"text":"I'm done"},{"text":"I want to quit"},{"text":"I have got to go"},{"text":"I d like to stop doing this"},{"text":"I am out of here"},{"text":"I am leaving"},{"text":"Hey bot go away"},{"text":"Have a nice day?"},{"text":"Goodbye"},{"text":"Good. bye."},{"text":"Going now"},{"text":"Time to go"},{"text":"That's everything"},{"text":"Go off"},{"text":"Go away"},{"text":"Get lost"},{"text":"Finished now, good bye"},{"text":"Ending this session"},{"text":"End trial"},{"text":"Cya later"}],"description":"End the conversation."},{"intent":"General_Negative_Feedback","examples":[{"text":"Stupid"},{"text":"Robots are stupid"},{"text":"Robots are boring"},{"text":"Quit annoying me"},{"text":"It is annoying"},{"text":"I hate you"},{"text":"I hate this!"},{"text":"I do not like you"},{"text":"Hate you"},{"text":"Everyone hates you"},{"text":"Do not like you?"},{"text":"You're too stupid"},{"text":"You're really irritating"},{"text":"You're really frustrating"},{"text":"You do not seem smart"},{"text":"You are very frustrating"},{"text":"You are on my nerves"},{"text":"You are having delusions"},{"text":"Why are you stupid?"},{"text":"Why are you so annoying?"}],"description":"Express unfavorable feedback."},{"intent":"General_Greetings","examples":[{"text":"What's up?"},{"text":"You there"},{"text":"Who is this?"},{"text":"Good day"},{"text":"Good evening"},{"text":"Good morning"},{"text":"Good to see you"},{"text":"Greetings"},{"text":"Have you been well?"},{"text":"Hello Agent"},{"text":"Hello I am looking for some help here"},{"text":"Hello"},{"text":"Hey how are you doing"},{"text":"Hey there all"},{"text":"Hey there"},{"text":"Hey twin"},{"text":"Hey you"},{"text":"Hi advisor"},{"text":"Hi there"},{"text":"How are things going?"},{"text":"How are you today?"},{"text":"How have you been?"},{"text":"How is it going?"},{"text":"How r u?"},{"text":"Looking good eve"},{"text":"Ok take me back"},{"text":"What's new?"}],"description":"Greet the bot."},{"intent":"good","examples":[{"text":"i'm okay"},{"text":"i'm happy most of the time and passing all my classes"},{"text":"I made a new friend"},{"text":"I'm doing well."},{"text":"I'm good."},{"text":"I'm happy."},{"text":"I'm fine."},{"text":"I'm okay."},{"text":"good"},{"text":"fine"},{"text":"yes"},{"text":"I had a wonderful day"},{"text":"great"},{"text":"terrific"},{"text":"I'm so happy and I'm passing all my classes and I just finished a project for this class."}],"description":""},{"intent":"bad","examples":[{"text":"Eh"},{"text":"My dog died"},{"text":"School is going fine but I have been stressed about this upcomgin exam"},{"text":"I'm sad."},{"text":"I'm not doing good."},{"text":"I'm not okay."},{"text":"I'm not doing well."},{"text":"i'm doing bad"},{"text":"not good"},{"text":"bad"},{"text":"terrible"},{"text":"I tripped today and got a cut"}],"description":""},{"intent":"General_Connect_to_Agent","examples":[{"text":"I want an agent to help me"},{"text":"I want to talk to a person"},{"text":"I would like to speak to a human"},{"text":"I would like to speak to someone"},{"text":"Is there anyone there I can actually talk to for real?"},{"text":"Need help from human"},{"text":"Operator please"},{"text":"Please assist me to get to an agent"},{"text":"Please connect me to a live agent"},{"text":"Please let me talk to a human being."},{"text":"Put me through to someone"},{"text":"Pls connect"},{"text":"Send me to an agent"},{"text":"Where is the closest agent?"},{"text":"Yes, take me to a real person"},{"text":"Can you assist me to connect to an agent?"},{"text":"Can I talk to someone?"},{"text":"Can I speak with somebody?"},{"text":"Can I speak to an advisor?"},{"text":"Can I speak to a live person?"},{"text":"Can I speak to a human please?"},{"text":"Can I connect to an agent?"},{"text":"Call agent"},{"text":"Agent help"},{"text":"A real agent, please."},{"text":"Can you connect me with a real person?"},{"text":"Connect me to a live operator please."},{"text":"Contact person"},{"text":"Could you please transfer me to your master?"},{"text":"Customer service representative please."},{"text":"Do not want a robot?"},{"text":"Hi can you transfer me"},{"text":"How can I skip the recorded menu and go straight to a live person?"},{"text":"I don't want to talk to a bot."},{"text":"I don't want to talk to you"},{"text":"I need to speak to a representative. How would I go about doing so?"},{"text":"I want a manager"},{"text":"I want agent"}],"description":"Request a human agent."},{"intent":"General_Security_Assurance","examples":[{"text":"Precautions hackers?"},{"text":"Are you safe on hackers?"},{"text":"Are you safe?"},{"text":"Can I be sure that my stored card details are held securely?"},{"text":"Conversation secure?"},{"text":"Customer info secured?"},{"text":"Do you have protection against hacks?"},{"text":"How do I know if my card info is kept safe?"},{"text":"How do I know this chat is not a scam?"},{"text":"How is my credit card info secured?"},{"text":"How safe is my data?"},{"text":"I'd like proof of a secure chat"},{"text":"In what way can I tell if my plastic is safe?"},{"text":"Is my card info secure?"},{"text":"Is my payment information secure?"},{"text":"Is there a reason to distrust this chat?"},{"text":"Is this a trusted chat site?"},{"text":"Is this an official chat?"},{"text":"Is this conversation secure?"},{"text":"Protection hacks?"},{"text":"Secure conversation?"},{"text":"What guards do you have in place to protect your customer's data?"},{"text":"What makes this chat trustworthy?"},{"text":"What safety measures are used to ensure that chat is secure?"},{"text":"Why would I trust this chat?"},{"text":"Will my conversation remain secured?"}],"description":"Express concerns about the security of the bot."},{"intent":"General_Positive_Feedback","examples":[{"text":"You are awesome"},{"text":"This is so cool"},{"text":"This is great"},{"text":"This is good"},{"text":"Thank you"},{"text":"Ok thank you"},{"text":"Love your work"},{"text":"Brilliant!"},{"text":"Can't believe you are that good"},{"text":"How cool is this?"},{"text":"I like what you did there! :)"},{"text":"I'm looking forward to working with you again! :)"},{"text":"You are the best"},{"text":"You're a genius!"},{"text":"You the man"},{"text":"You gave me exactly what I need!"},{"text":"You are wonderful"},{"text":"You've been so helpful :)"},{"text":"You are great"}],"description":"Express positive sentiment or gratitude."},{"intent":"General_Human_or_Bot","examples":[{"text":"Are you a robot?"},{"text":"Tell me, are you a human or no?"},{"text":"Is this a computer?"},{"text":"How can you prove you are a human?"},{"text":"Are you real?"},{"text":"Are you human?"},{"text":"Are you even real?"},{"text":"Are you a human or a bot?"},{"text":"Am I talking to a person or am I talking to an AI?"},{"text":"Am I talking to a Bot?"},{"text":"Am I talking to Watson?"},{"text":"Am I chatting with a human?"}],"description":"Ask if speaking to a human or a bot."},{"intent":"General_About_You","examples":[{"text":"About you"},{"text":"How old are you?"},{"text":"How do you function?"},{"text":"How can I configure you?"},{"text":"Do you know who you are?"},{"text":"Do you have a name?"},{"text":"Describe your self"},{"text":"Can I use another language?"},{"text":"Why are you here?"},{"text":"What should I know about you?"},{"text":"What's your name?"},{"text":"Where are you from?"},{"text":"Where were you born?"},{"text":"Who are you?"},{"text":"I want to set up the chat bot for my shop"},{"text":"Introduce your self"},{"text":"Let us talk about you"},{"text":"Tell me about your life"},{"text":"Tell me something about yourself"},{"text":"What languages do you speak?"}],"description":"Request generic personal attributes."},{"intent":"General_Jokes","examples":[{"text":"I'm bored"},{"text":"Surprise me with something hilarious"},{"text":"Tell me a joke"},{"text":"Tell me something funny"},{"text":"What do you do for fun?"},{"text":"What is your favorite joke?"},{"text":"Another joke"},{"text":"Are there jokes?"},{"text":"Can you tell a joke?"},{"text":"Can you tell me a joke?"},{"text":"Do you have a joke?"},{"text":"Do you have humor?"},{"text":"Do you like fun?"},{"text":"Do you like humor?"},{"text":"I am getting bored"},{"text":"I want a joke"},{"text":"One more joke"}],"description":"Request a joke."},{"intent":"General_Agent_Capabilities","examples":[{"text":"Tell me something"},{"text":"What are my options that you can help with?"},{"text":"What are my options?"},{"text":"How can you solve my problems?"},{"text":"How can you help me?"},{"text":"Where can I find the frequently asked questions?"},{"text":"What kinds of things can you do?"},{"text":"What are you able to deal with?"},{"text":"What are you able to understand?"},{"text":"What are you capable of?"},{"text":"What are you good at?"},{"text":"What are you used for?"},{"text":"What are your skills?"},{"text":"What can I ask you to do?"},{"text":"What do you do?"},{"text":"What do you handle?"},{"text":"What else can you help me with?"},{"text":"What features are in here?"},{"text":"What is this 4?"},{"text":"Can you please give me a list of the types of things you can help me with?"},{"text":"Can you tell me what services you are able to help me with?"},{"text":"Do you have a list of things I can talk to you about?"},{"text":"Help now"},{"text":"Hi, what do you do?"},{"text":"How can I use you?"},{"text":"How do I use you?"},{"text":"I do not know what to ask"},{"text":"I'd like to know what type of questions you can answer for me."},{"text":"Is there anything you can help me with?"},{"text":"Tell me about what kind of things you do?"}],"description":"Request capabilities of the bot."}],"entities":[{"entity":"risk_factor","values":[{"type":"synonyms","value":"low self-esteem","synonyms":[]},{"type":"synonyms","value":"self-critical","synonyms":[]},{"type":"synonyms","value":"pessimistic","synonyms":["gloomier","bleak","downbeat","cynical"]},{"type":"synonyms","value":"trauma","synonyms":[]},{"type":"synonyms","value":"anxiety","synonyms":["stress","tension","tense","nervous","stressed","anxious","strain"]},{"type":"synonyms","value":"eating disorder","synonyms":["bulimia","anorexia","binge eating"]},{"type":"synonyms","value":"post-traumatic stress disorder","synonyms":["ptsd"]},{"type":"synonyms","value":"drug abuse","synonyms":[]},{"type":"synonyms","value":"chronic illness","synonyms":[]},{"type":"synonyms","value":"medication","synonyms":["prescription","medications","drugs","medicines","prescribed","treatment","pills","meds","painkillers"]}],"fuzzy_match":true},{"entity":"symptom","values":[{"type":"synonyms","value":"sadness","synonyms":["sorrow","grief","regret","unhappiness","sad","bitterness","despair","anguish","hopelessness","misery","despondency","agony","remorse","desperation","helplessness","guilt","discouragement","powerlessness","pity","dismay","loneliness","shame","disgust","dissatisfaction","displeasure","discontent"]},{"type":"synonyms","value":"emptiness","synonyms":["nothingness","loneliness","hopelessness","despair","aloneness","meaninglessness","sadness","blankness","formlessness","longing","despondency","sorrow","desperation","powerlessness","helplessness","grief","unhappiness","desolation","regret"]},{"type":"synonyms","value":"hopelessness","synonyms":["despair","powerlessness","helplessness","desperation","despondency","worthlessness","loneliness","sadness","discouragement","unhappiness","anguish","dismay","uneasiness","uselessness","indifference"]},{"type":"synonyms","value":"irritability","synonyms":["sleeplessness","impulsivity","drowsiness","sleepiness","restlessness","moodiness","tearfulness","lethargy","tiredness","insomnia","somnolence","fatigue","weariness","agitation","apathy","listlessness","dizziness","grogginess"]},{"type":"synonyms","value":"suicide","synonyms":["suicidal","death","dying","ideation","want to kill myself","want to die"]},{"type":"synonyms","value":"self-harm","synonyms":["ideations","suicidality","self-injury","self-mutilation","suicide"]},{"type":"synonyms","value":"lack of energy","synonyms":["tired","tiredness","exhaustion","exhausted","bored","apathetic"]},{"type":"synonyms","value":"stress","synonyms":["tension","anxiety","strain","pressure","duress","fatigue","uneasiness","depression","unease","apprehension","weariness","anxiousness"]},{"type":"synonyms","value":"worthlessness","synonyms":["uselessness","futility","hopelessness","unworthiness","powerlessness","inadequacy","helplessness","purposelessness","despondency","unworthy","despair","discouragement","desperation","meaninglessness","dejection","aimlessness","disinterest","unhappiness","apathy","loneliness"]},{"type":"synonyms","value":"frustration","synonyms":["dissatisfaction","discontent","anger","unhappiness","resentment","anguish","dismay","displeasure","unease","indignation","exasperation","disdain","discontentment"]},{"type":"synonyms","value":"guilt","synonyms":["remorse","hopelessness","grief","sadness","resentment","helplessness","anguish","inadequacy","loneliness","sorrow","despair","powerlessness","anger","unhappiness","heartache","regret","bitterness","desperation","agony"]},{"type":"synonyms","value":"insomnia","synonyms":["sleeplessness","migraines","restlessness","lack of sleep"]},{"type":"synonyms","value":"restlessness","synonyms":["agitation","irritability","sleeplessness","listlessness","nervousness","moodiness","jitteriness","uneasiness","anxiety","unease","insomnia","anxiousness","disquiet","drowsiness","sleepiness","malaise","disorientation"]}],"fuzzy_match":true},{"entity":"reply","values":[{"type":"synonyms","value":"yes","synonyms":["yeah","yep","yup","sure"]},{"type":"synonyms","value":"no","synonyms":["nope","nah","naw"]},{"type":"synonyms","value":"not sure","synonyms":["i don't know","dunno"]}],"fuzzy_match":true}],"language":"en","metadata":{"api_version":{"major_version":"v1","minor_version":"2018-07-10"}},"description":"","dialog_nodes":[{"type":"standard","title":"@reply no","output":{"generic":[{"values":[{"text":"It looks like you might just be in a slump! It's perfectly normal to feel sad every now and then. Here are some ways to feel better: https://www.mayoclinic.org/healthy-lifestyle/stress-management/basics/stress-relief/hlv-20049495"}],"response_type":"text","selection_policy":"sequential"}]},"parent":"node_4_1541543603823","metadata":{},"next_step":{"behavior":"jump_to","selector":"body","dialog_node":"node_3_1541569329626"},"conditions":"@reply:no","dialog_node":"node_2_1541569092502","previous_sibling":"node_1_1541568798317"},{"type":"standard","title":"@reply yes","output":{"generic":[{"values":[{"text":"This does not sound good. Have you felt any of the following: anxiety, low self-esteem, or abuse?"}],"response_type":"text","selection_policy":"sequential"}]},"parent":"node_4_1541543603823","metadata":{},"next_step":{"behavior":"jump_to","selector":"user_input","dialog_node":"node_10_1541558924628"},"conditions":"@reply:yes","dialog_node":"node_1_1541568798317"},{"type":"response_condition","output":{"generic":[{"values":[{"text":"Good morning. How are you doing today?"}],"response_type":"text","selection_policy":"sequential"}]},"parent":"Welcome","disabled":true,"metadata":{},"dialog_node":"node_1_1541540350688","previous_sibling":"node_2_1541609017568"},{"type":"standard","title":"Negative/Neutral emotion","output":{"generic":[{"values":[{"text":"I detected $user.tone.emotion.current. You don't sound very happy. Can you elaborate on what's bothering you?"}],"response_type":"text","selection_policy":"sequential"}]},"parent":"Welcome","metadata":{},"conditions":"#bad || $user.tone.emotion.current == \"sadness\" && $user.tone.emotion.current == \"anger\" && $user.tone.emotion.current == \"fear\" && $user.tone.emotion.current == \"analytical\" && $user.tone.emotion.current == \"tentative\"","dialog_node":"node_2_1541609017568","previous_sibling":"node_1_1541608845167"},{"type":"standard","title":"Positive emotion","output":{"generic":[{"values":[{"text":" I detected $user.tone.emotion.current. That's good! Can you elaborate?"}],"response_type":"text","selection_policy":"sequential"}]},"parent":"Welcome","metadata":{},"conditions":"#good || $user.tone.emotion.current == \"joy\"","dialog_node":"node_1_1541608845167"},{"type":"standard","title":"no symptom END","output":{"generic":[{"values":[{"text":"I'm glad to hear you are doing well! If you are ever stressed out or anxious about something, here is a resource to counter such emotion: https://www.mayoclinic.org/healthy-lifestyle/stress-management/basics/stress-relief/hlv-20049495"}],"response_type":"text","selection_policy":"sequential"}]},"metadata":{},"next_step":{"behavior":"jump_to","selector":"body","dialog_node":"node_3_1541569329626"},"conditions":"#good","dialog_node":"node_11_1541559205426","previous_sibling":"node_10_1541558924628"},{"type":"standard","title":"@symptom","output":{"generic":[{"values":[{"text":"I'm sorry to hear that you have been feeling @symptom"}],"response_type":"text","selection_policy":"sequential"},{"values":[{"text":"Have you been feeling this way for more than two weeks?"}],"response_type":"text","selection_policy":"sequential"}]},"metadata":{},"conditions":"@symptom && intents[0].confidence > 0.7","dialog_node":"node_4_1541543603823","previous_sibling":"node_1_1541612171135"},{"type":"standard","title":"@risk_factor","output":{"generic":[{"values":[{"text":"Having @risk_factor can be a risk factor for depression. Read more about depression here: https://www.nimh.nih.gov/health/publications/depression/index.shtml"}],"response_type":"text","selection_policy":"sequential"}]},"metadata":{},"conditions":"@risk_factor && intents[0].confidence > 0.7","digress_in":"does_not_return","dialog_node":"node_10_1541558924628","previous_sibling":"node_4_1541543603823"},{"type":"standard","title":"Anything else","output":{"generic":[{"values":[{"text":"I didn't understand. You can try rephrasing."},{"text":"Can you reword your statement? I'm not understanding."},{"text":"I didn't get your meaning."}],"response_type":"text","selection_policy":"sequential"}]},"metadata":{},"conditions":"anything_else","dialog_node":"Anything else","previous_sibling":"node_3_1541569329626"},{"type":"standard","title":"end","output":{"generic":[{"values":[{"text":"Goodbye!"},{"text":"Have a good day!"}],"response_type":"text","selection_policy":"sequential"}]},"context":{"conversationEnd":true},"metadata":{},"conditions":"#General_Ending","dialog_node":"node_3_1541569329626","previous_sibling":"node_3_1541543278735"},{"type":"standard","title":"depression END","output":{"generic":[{"values":[{"text":"You should tell your doctor about how you have been feeling this way. Meanwhile, here is a resource on depression and its symptoms: https://www.nimh.nih.gov/health/publications/depression/index.shtml"}],"response_type":"text","selection_policy":"sequential"}]},"metadata":{},"next_step":{"behavior":"jump_to","selector":"body","dialog_node":"node_3_1541569329626"},"conditions":"@symptom","dialog_node":"node_3_1541543278735","previous_sibling":"node_11_1541559205426"},{"type":"standard","title":"suicide","output":{"generic":[{"values":[{"text":"Please see a professional to talk about how you're feeling. If you need someone to talk to, call the National Suicide Prevention Lifeline at 1-800-273-8255."}],"response_type":"text","selection_policy":"sequential"}]},"metadata":{},"conditions":"@symptom:suicide","digress_in":"does_not_return","dialog_node":"node_1_1541612171135","previous_sibling":"Welcome"},{"type":"standard","title":"Welcome","output":{"generic":[{"values":[{"text":"Hello. How are you doing today?"}],"response_type":"text","selection_policy":"sequential"}]},"metadata":{"_customization":{"mcr":false}},"conditions":"conversation_start","digress_in":"does_not_return","dialog_node":"Welcome","digress_out":"allow_all"}],"workspace_id":"1e7277b6-c5ec-4e49-b872-4f4a4caf5d25","counterexamples":[],"system_settings":{"tooling":{"store_generic_responses":true},"disambiguation":{"prompt":"Did you mean:","none_of_the_above_prompt":"None of the above"},"human_agent_assist":{"prompt":"Did you mean:"}},"learning_opt_out":false}